ai_client.cp39-win_amd64.pyd
autonomous_doc_generator.cp39-win_amd64.pyd
comment_extractor.cp39-win_amd64.pyd
comment_injector.cp39-win_amd64.pyd
config.cp39-win_amd64.pyd
config_wizard.cp39-win_amd64.pyd
doc_generator.cp39-win_amd64.pyd
embedding_client.cp39-win_amd64.pyd
encrypt_key.cp39-win_amd64.pyd
git_operations.cp39-win_amd64.pyd
i18n.cp39-win_amd64.pyd
i18n_en.cp39-win_amd64.pyd
i18n_zh.cp39-win_amd64.pyd
install_wizard.cp39-win_amd64.pyd
key_obfuscator.cp39-win_amd64.pyd
loading_utils.cp39-win_amd64.pyd
main.cp39-win_amd64.pyd
mcp_client.cp39-win_amd64.pyd
mcp_server.cp39-win_amd64.pyd
prompt_enhancer.cp39-win_amd64.pyd
vector_db.cp39-win_amd64.pyd
vulnerability_scanner.cp39-win_amd64.pyd
ails_cli_tool-1.1.5.dist-info/licenses/LICENSE
ails_cli_tool-1.1.5.dist-info/METADATA
ails_cli_tool-1.1.5.dist-info/WHEEL
ails_cli_tool-1.1.5.dist-info/entry_points.txt
ails_cli_tool-1.1.5.dist-info/top_level.txt
ails_cli_tool-1.1.5.dist-info/RECORD
