Metadata-Version: 2.4
Name: ails-cli-tool
Version: 1.1.5
Summary: AI-powered directory scanner and project analyzer
Author: oldjs
License: MIT
Project-URL: Homepage, https://github.com/oldjs/ails
Project-URL: Bug Tracker, https://github.com/oldjs/ails/issues
Keywords: ai,directory,scanner,analyzer,cli
Classifier: Development Status :: 3 - Alpha
Classifier: Intended Audience :: Developers
Classifier: Topic :: Software Development :: Build Tools
Classifier: Programming Language :: Python :: 3
Classifier: Programming Language :: Python :: 3.8
Classifier: Programming Language :: Python :: 3.9
Classifier: Programming Language :: Python :: 3.10
Classifier: Programming Language :: Python :: 3.11
Classifier: Programming Language :: Python :: 3.12
Classifier: Operating System :: OS Independent
Requires-Python: >=3.8
License-File: LICENSE
Requires-Dist: fastmcp>=0.1.0
Requires-Dist: openai>=1.0.0
Requires-Dist: python-dotenv>=1.0.0
Requires-Dist: requests>=2.25.0
Requires-Dist: sqlite-vec>=0.1.0
Requires-Dist: pathspec>=0.11.0
Requires-Dist: pyperclip>=1.8.0
Dynamic: license-file
